[
  {
    "id": "qPWzha",
    "name": "Cambridge",
    "url": "https://dictionary.cambridge.org/dictionary/english/{{phrase}}"
  },
  {
    "id": "lJrlAs",
    "name": "Collins",
    "url": "https://www.collinsdictionary.com/dictionary/english/{{phrase}}"
  },
  {
    "id": "XhVTIJ",
    "name": "Vocabulary",
    "url": "https://www.vocabulary.com/dictionary/{{phrase}}"
  },
  {
    "id": "eNeNVw",
    "name": "MacMillan",
    "url": "https://www.macmillandictionary.com/dictionary/british/{{phrase}}"
  },
  {
    "id": "7grJ1s",
    "name": "Merriam Webster",
    "url": "https://www.merriam-webster.com/dictionary/{{phrase}}"
  },
  {
    "id": "KiugJU",
    "name": "Longman",
    "url": "https://www.ldoceonline.com/dictionary/{{phrase}}"
  },
  {
    "id": "MK88n2",
    "name": "Oxford",
    "url": "https://www.oxfordlearnersdictionaries.com/spellcheck/english/?q={{phrase}}"
  },
  {
    "id": "xiQog2",
    "name": "Dictionary",
    "url": "https://www.dictionary.com/browse/{{phrase}}"
  },
  {
    "id": "kE10DV",
    "name": "The free dictionary",
    "url": "https://www.thefreedictionary.com/{{phrase}}"
  }
]
